{
    "URL": "https://doi.org/10.1371/journal.pntd.0010099",
    "Published": "February 2, 2022",
    "Subject_Areas": [
        "Echinococcosis",
        "Chemokines",
        "Cytokines",
        "Larvae",
        "Parasitic diseases",
        "Immune response",
        "Progressive diseases",
        "Enzyme-linked immunoassays"
    ],
    "Authors": {
        "Beate Gr\u00fcner": [
            "University Hospital of Ulm, Department of Internal Medicine III, Division of Infectious Diseases, Ulm, Germany"
        ],
        "Lynn Peters": [
            "University Hospital of Ulm, Department of Internal Medicine III, Division of Infectious Diseases, Ulm, Germany"
        ],
        "Andreas Hillenbrand": [
            "Department of General and Visceral Surgery, Ulm University Hospital, Ulm, Germany"
        ],
        "Patrick Vo\u00dfberg": [
            "University Clinics T\u00fcbingen, Institute for Tropical Medicine, Eberhard-Karls University, T\u00fcbingen, Germany"
        ],
        "Jonas Schweiker": [
            "University Clinics T\u00fcbingen, Institute for Tropical Medicine, Eberhard-Karls University, T\u00fcbingen, Germany"
        ],
        "Elisabeth G. Rollmann": [
            "University Clinics T\u00fcbingen, Institute for Tropical Medicine, Eberhard-Karls University, T\u00fcbingen, Germany"
        ],
        "Laura H. Rodriguez": [
            "University Clinics T\u00fcbingen, Institute for Tropical Medicine, Eberhard-Karls University, T\u00fcbingen, Germany"
        ],
        "Jasmin Blumhardt": [
            "University Clinics T\u00fcbingen, Institute for Tropical Medicine, Eberhard-Karls University, T\u00fcbingen, Germany"
        ],
        "Sanne Burkert": [
            "University Hospital of Ulm, Department of Internal Medicine III, Division of Infectious Diseases, Ulm, Germany"
        ],
        "Peter Kern": [
            "University Hospital of Ulm, Department of Internal Medicine III, Division of Infectious Diseases, Ulm, Germany"
        ],
        "Carsten K\u00f6hler": [
            "University Clinics T\u00fcbingen, Institute for Tropical Medicine, Eberhard-Karls University, T\u00fcbingen, Germany"
        ],
        "Peter T. Soboslay": [
            "University Clinics T\u00fcbingen, Institute for Tropical Medicine, Eberhard-Karls University, T\u00fcbingen, Germany"
        ]
    }
}