{
    "Title": "Loxosceles gaucho Venom-Induced Acute Kidney Injury – In Vivo and In Vitro Studies",
    "URL": "https://doi.org/10.1371/journal.pntd.0001182",
    "Published": "May 31, 2011",
    "Subject_Areas": [
        "Venoms",
        "Spiders",
        "Hemoglobin",
        "Kidneys",
        "Rhabdomyolysis",
        "Glomerular filtration rate",
        "Blood pressure",
        "Renal system"
    ],
    "Authors": {
        "Rui V. Lucato Jr": [
            "Division of Nephrology, São José do Rio Preto Medical School, São José do Rio Preto, Brazil",
            "Division of Nephrology, São Paulo Federal University, São Paulo, Brazil"
        ],
        "Regina C. R. M. Abdulkader": [
            "Division of Nephrology, University of São Paulo Medical School, São Paulo, Brazil"
        ],
        "Katia C. Barbaro": [
            "Laboratory of Immunopathology, Butantan Institute, São Paulo, Brazil"
        ],
        "Glória E. Mendes": [
            "Division of Nephrology, São José do Rio Preto Medical School, São José do Rio Preto, Brazil"
        ],
        "Isac Castro": [
            "Division of Nephrology, University of São Paulo Medical School, São Paulo, Brazil"
        ],
        "Maria A. S. F. Baptista": [
            "Division of Nephrology, São José do Rio Preto Medical School, São José do Rio Preto, Brazil"
        ],
        "Patrícia M. Cury": [
            "Department of Pathology, São José do Rio Preto Medical School, São José do Rio Preto, Brazil"
        ],
        "Denise M. C. Malheiros": [
            "Division of Nephrology, University of São Paulo Medical School, São Paulo, Brazil"
        ],
        "Nestor Schor": [
            "Division of Nephrology, São Paulo Federal University, São Paulo, Brazil"
        ],
        "Luis Yu": [
            "Division of Nephrology, University of São Paulo Medical School, São Paulo, Brazil"
        ],
        "Emmanuel A. Burdmann": [
            "Division of Nephrology, São José do Rio Preto Medical School, São José do Rio Preto, Brazil"
        ]
    }
}