{
    "URL": "https://doi.org/10.1371/journal.pntd.0010385",
    "Published": "August 30, 2022",
    "Subject_Areas": [
        "Mycetoma",
        "Fungi",
        "Metagenomics",
        "Fusarium",
        "Sudan",
        "Acremonium",
        "Aspergillus",
        "Madurella"
    ],
    "Authors": {
        "Antonella Santona": [
            "Department of Biomedical Sciences, University of Sassari, Sassari, Italy"
        ],
        "Najwa A. Mhmoud": [
            "Mycetoma Research Centre, University of Khartoum, Khartoum, Sudan",
            "Faculty of Medical Laboratory Sciences, University of Khartoum, Khartoum, Sudan"
        ],
        "Emmanuel Edwar Siddig": [
            "Mycetoma Research Centre, University of Khartoum, Khartoum, Sudan",
            "Faculty of Medical Laboratory Sciences, University of Khartoum, Khartoum, Sudan"
        ],
        "Massimo Deligios": [
            "Department of Biomedical Sciences, University of Sassari, Sassari, Italy"
        ],
        "Maura Fiamma": [
            "Department of Biomedical Sciences, University of Sassari, Sassari, Italy"
        ],
        "Bianca Paglietti": [
            "Department of Biomedical Sciences, University of Sassari, Sassari, Italy"
        ],
        "Sahar Mubarak Bakhiet": [
            "Mycetoma Research Centre, University of Khartoum, Khartoum, Sudan",
            "Institute for Endemic Diseases, University of Khartoum, Khartoum, Sudan"
        ],
        "Salvatore Rubino": [
            "Department of Biomedical Sciences, University of Sassari, Sassari, Italy"
        ],
        "Ahmed Hassan Fahal": [
            "Mycetoma Research Centre, University of Khartoum, Khartoum, Sudan"
        ]
    }
}