{
    "Title": "Effects of Deworming on Malnourished Preschool Children in India: An Open-Labelled, Cluster-Randomized Trial",
    "URL": "https://doi.org/10.1371/journal.pntd.0000223",
    "Published": "April 16, 2008",
    "Subject_Areas": [
        "Weight gain",
        "Children",
        "Schools",
        "Body weight",
        "India",
        "Nematode infections",
        "Urban infrastructure",
        "Vitamin A"
    ],
    "Authors": {
        "Shally Awasthi": [
            "Department of Paediatrics, King George's Medical University, Lucknow, India"
        ],
        "Richard Peto": [
            "Clinical Trial Service Unit, University of Oxford, Oxford, United Kingdom"
        ],
        "Vinod K. Pande": [
            "Department of Paediatrics, King George's Medical University, Lucknow, India"
        ],
        "Robert H. Fletcher": [
            "Harvard Medical School, Harvard University, Boston, Massachusetts, United States of America"
        ],
        "Simon Read": [
            "Clinical Trial Service Unit, University of Oxford, Oxford, United Kingdom"
        ],
        "Donald A. P. Bundy": [
            "Human Development Division, The World Bank, Washington, D.C., United States of America"
        ]
    }
}