{
    "Title": "Murine Dendritic Cells Transcriptional Modulation upon Paracoccidioides brasiliensis Infection",
    "URL": "https://doi.org/10.1371/journal.pntd.0001459",
    "Published": "January 3, 2012",
    "Subject_Areas": [
        "Yeast infections",
        "Microarrays",
        "Gene expression",
        "Paracoccidioides brasiliensis",
        "Cytokines",
        "Fungal genetics",
        "Fungi",
        "Gene regulation"
    ],
    "Authors": {
        "Aldo H. Tavares": [
            "Faculdade de Ceilândia, Universidade de Brasília, Brasília, Brasil"
        ],
        "Lorena S. Derengowski": [
            "Departamento de Biologia Celular, Universidade de Brasília, Brasília, Brasil"
        ],
        "Karen S. Ferreira": [
            "Departamento de Ciências Biológicas, Universidade Federal de São Paulo, São Paulo, Brasil"
        ],
        "Simoneide S. Silva": [
            "Departamento de Biologia Celular, Universidade de Brasília, Brasília, Brasil"
        ],
        "Cláudia Macedo": [
            "Departamento de Genética, Faculdade de Medicina de Ribeirão Preto, Universidade de São Paulo, São Paulo, Brasil"
        ],
        "Anamélia L. Bocca": [
            "Departamento de Biologia Celular, Universidade de Brasília, Brasília, Brasil"
        ],
        "Geraldo A. Passos": [
            "Departamento de Genética, Faculdade de Medicina de Ribeirão Preto, Universidade de São Paulo, São Paulo, Brasil"
        ],
        "Sandro R. Almeida": [
            "Departamento de Análises Clínicas e Toxicológicas, Faculdade de Ciências Farmacêuticas, Universidade de São Paulo, São Paulo, Brasil"
        ],
        "Ildinete Silva-Pereira": [
            "Departamento de Biologia Celular, Universidade de Brasília, Brasília, Brasil"
        ]
    }
}