{
    "Title": "Synergy of Omeprazole and Praziquantel In Vitro Treatment against Schistosoma mansoni Adult Worms",
    "URL": "https://doi.org/10.1371/journal.pntd.0004086",
    "Published": "September 24, 2015",
    "Subject_Areas": [
        "Gene expression",
        "Schistosoma mansoni",
        "Microarrays",
        "Genetic networks",
        "Drug therapy",
        "Interaction networks",
        "Schistosoma",
        "Functional analysis"
    ],
    "Authors": {
        "Giulliana T. Almeida": [
            "Departamento de Bioquímica, Instituto de Química, Universidade de São Paulo, São Paulo, Brazil"
        ],
        "Regina C. G. Lage": [
            "Genomics and Computational Biology Group, Centro de Pesquisas René Rachou - FIOCRUZ, Belo Horizonte, Minas Gerais, Brazil"
        ],
        "Leticia Anderson": [
            "Departamento de Bioquímica, Instituto de Química, Universidade de São Paulo, São Paulo, Brazil"
        ],
        "Thiago M. Venancio": [
            "Departamento de Bioquímica, Instituto de Química, Universidade de São Paulo, São Paulo, Brazil"
        ],
        "Helder I. Nakaya": [
            "Departamento de Bioquímica, Instituto de Química, Universidade de São Paulo, São Paulo, Brazil"
        ],
        "Patrícia A. Miyasato": [
            "Instituto Butantan, São Paulo, São Paulo, Brazil"
        ],
        "Henrique K. Rofatto": [
            "Instituto Butantan, São Paulo, São Paulo, Brazil"
        ],
        "Adhemar Zerlotini": [
            "Genomics and Computational Biology Group, Centro de Pesquisas René Rachou - FIOCRUZ, Belo Horizonte, Minas Gerais, Brazil"
        ],
        "Eliana Nakano": [
            "Instituto Butantan, São Paulo, São Paulo, Brazil"
        ],
        "Guilherme Oliveira": [
            "Genomics and Computational Biology Group, Centro de Pesquisas René Rachou - FIOCRUZ, Belo Horizonte, Minas Gerais, Brazil",
            "Vale Technology Institute, Belém, Pará, Brazil"
        ],
        "Sergio Verjovski-Almeida": [
            "Departamento de Bioquímica, Instituto de Química, Universidade de São Paulo, São Paulo, Brazil",
            "Instituto Butantan, São Paulo, São Paulo, Brazil"
        ]
    }
}