{
    "Title": "Interruption of persistent exposure to leprosy combined or not with recent BCG vaccination enhances the response to Mycobacterium leprae specific antigens",
    "URL": "https://doi.org/10.1371/journal.pntd.0005560",
    "Published": "May 3, 2017",
    "Subject_Areas": [
        "Mycobacterium leprae",
        "Leprosy",
        "Vaccination and immunization",
        "Immune response",
        "T cells",
        "Cytotoxic T cells",
        "Inflammation",
        "Medical risk factors"
    ],
    "Authors": {
        "Fernanda Marques de Carvalho": [
            "Laboratory of Cellular Microbiology, Oswaldo Cruz Institute, FIOCRUZ, Rio de Janeiro, Brazil"
        ],
        "Luciana Silva Rodrigues": [
            "Laboratory of Cellular Microbiology, Oswaldo Cruz Institute, FIOCRUZ, Rio de Janeiro, Brazil"
        ],
        "Nádia Cristina Duppre": [
            "Leprosy Laboratory, Oswaldo Cruz Institute, FIOCRUZ, Rio de Janeiro, Brazil"
        ],
        "Iris Maria Peixoto Alvim": [
            "Laboratory of Cellular Microbiology, Oswaldo Cruz Institute, FIOCRUZ, Rio de Janeiro, Brazil"
        ],
        "Marcelo Ribeiro-Alves": [
            "Laboratory of Clinical Research in DST- AIDS, Institute of Clinical Research Evandro Chagas, FIOCRUZ, Rio de Janeiro, Rio de Janeiro, Brazil"
        ],
        "Roberta Olmo Pinheiro": [
            "Leprosy Laboratory, Oswaldo Cruz Institute, FIOCRUZ, Rio de Janeiro, Brazil"
        ],
        "Euzenir Nunes Sarno": [
            "Leprosy Laboratory, Oswaldo Cruz Institute, FIOCRUZ, Rio de Janeiro, Brazil"
        ],
        "Maria Cristina Vidal Pessolani": [
            "Laboratory of Cellular Microbiology, Oswaldo Cruz Institute, FIOCRUZ, Rio de Janeiro, Brazil"
        ],
        "Geraldo Moura Batista Pereira": [
            "Laboratory of Cellular Microbiology, Oswaldo Cruz Institute, FIOCRUZ, Rio de Janeiro, Brazil"
        ]
    }
}