{
    "URL": "https://doi.org/10.1371/journal.pntd.0002036",
    "Published": "January 31, 2013",
    "Subject_Areas": [
        "Campylobacter",
        "Diarrhea",
        "Medical risk factors",
        "Campylobacteriosis",
        "Weight gain",
        "Opportunistic infections",
        "Blood",
        "Malnutrition"
    ],
    "Authors": {
        "Gwenyth Lee": [
            "Department of International Health, Johns Hopkins Bloomberg School of Public Health, Baltimore, Maryland, United States of America"
        ],
        "William Pan": [
            "Duke Global Health Institute, Duke University, Durham, North Carolina, United States of America"
        ],
        "Pablo Pe\u00f1ataro Yori": [
            "Department of International Health, Johns Hopkins Bloomberg School of Public Health, Baltimore, Maryland, United States of America",
            "Biomedical Research, Asociaci\u00f3n Ben\u00e9fica PRISMA, Iquitos, Peru"
        ],
        "Maribel Paredes Olortegui": [
            "Department of International Health, Johns Hopkins Bloomberg School of Public Health, Baltimore, Maryland, United States of America",
            "Biomedical Research, Asociaci\u00f3n Ben\u00e9fica PRISMA, Iquitos, Peru"
        ],
        "Drake Tilley": [
            "U.S. Naval Medical Research Unit Six, Lima, Peru"
        ],
        "Michael Gregory": [
            "U.S. Naval Medical Research Unit Six, Lima, Peru"
        ],
        "Richard Oberhelman": [
            "Department of Tropical Medicine, Tulane School of Public Health, New Orleans, Louisiana, United States of America"
        ],
        "Rosa Burga": [
            "U.S. Naval Medical Research Unit Six, Lima, Peru"
        ],
        "Cesar Banda Chavez": [
            "Biomedical Research, Asociaci\u00f3n Ben\u00e9fica PRISMA, Iquitos, Peru"
        ],
        "Margaret Kosek": [
            "Department of International Health, Johns Hopkins Bloomberg School of Public Health, Baltimore, Maryland, United States of America",
            "Biomedical Research, Asociaci\u00f3n Ben\u00e9fica PRISMA, Iquitos, Peru"
        ]
    }
}