{
    "Title": "A cross-sectional investigation of Leptospira at the wildlife-livestock interface in New Zealand",
    "URL": "https://doi.org/10.1371/journal.pntd.0011624",
    "Published": "September 6, 2023",
    "Subject_Areas": [
        "Livestock",
        "Farms",
        "Wildlife",
        "Leptospira",
        "Opossums",
        "Sheep",
        "Hedgehogs",
        "Domestic animals"
    ],
    "Authors": {
        "Marie Moinet": [
            "Tāwharau Ora School of Veterinary Science, Massey University, Palmerston North, New Zealand"
        ],
        "Hedwich Oosterhof": [
            "Faculty of Veterinary Medicine, Utrecht University, Utrecht, The Netherlands"
        ],
        "Shahista Nisa": [
            "Tāwharau Ora School of Veterinary Science, Massey University, Palmerston North, New Zealand"
        ],
        "Neville Haack": [
            "Tāwharau Ora School of Veterinary Science, Massey University, Palmerston North, New Zealand"
        ],
        "David A. Wilkinson": [
            "Tāwharau Ora School of Veterinary Science, Massey University, Palmerston North, New Zealand",
            "New Zealand Food Safety Science & Research Centre, Hopkirk Research Institute, Palmerston North, New Zealand"
        ],
        "Danielle Aberdein": [
            "Tāwharau Ora School of Veterinary Science, Massey University, Palmerston North, New Zealand"
        ],
        "James C. Russell": [
            "School of Biological Sciences and Department of Statistics, University of Auckland, New Zealand"
        ],
        "Emilie Vallée": [
            "Tāwharau Ora School of Veterinary Science, Massey University, Palmerston North, New Zealand"
        ],
        "Julie Collins-Emerson": [
            "Tāwharau Ora School of Veterinary Science, Massey University, Palmerston North, New Zealand"
        ],
        "Cord Heuer": [
            "Tāwharau Ora School of Veterinary Science, Massey University, Palmerston North, New Zealand"
        ],
        "Jackie Benschop": [
            "Tāwharau Ora School of Veterinary Science, Massey University, Palmerston North, New Zealand"
        ]
    }
}