{
    "Title": "Accuracy of different diagnostic techniques for Schistosoma haematobium to estimate treatment needs in Zimbabwe: Application of a hierarchical Bayesian egg count model",
    "URL": "https://doi.org/10.1371/journal.pntd.0008451",
    "Published": "August 20, 2020",
    "Subject_Areas": [
        "Urine",
        "Schistosoma haematobium",
        "Blood",
        "Diagnostic medicine",
        "Schools",
        "Eggs",
        "Zimbabwe",
        "Schistosomiasis"
    ],
    "Authors": {
        "Nicholas Midzi": [
            "National Institute of Health Research, Ministry of Health and Child Care, Harare, Zimbabwe"
        ],
        "Oliver B\u00e4renbold": [
            "Swiss Tropical and Public Health Institute, Basel, Switzerland",
            "Faculty of Science, University of Basel, Basel, Switzerland"
        ],
        "Portia Manangazira": [
            "National Institute of Health Research, Ministry of Health and Child Care, Harare, Zimbabwe"
        ],
        "Isaac Phiri": [
            "National Institute of Health Research, Ministry of Health and Child Care, Harare, Zimbabwe"
        ],
        "Masceline J. Mutsaka-Makuvaza": [
            "National Institute of Health Research, Ministry of Health and Child Care, Harare, Zimbabwe",
            "Department of Medical Microbiology, University of Zimbabwe, Harare, Zimbabwe"
        ],
        "Gibson Mhlanga": [
            "National Institute of Health Research, Ministry of Health and Child Care, Harare, Zimbabwe"
        ],
        "J\u00fcrg Utzinger": [
            "Swiss Tropical and Public Health Institute, Basel, Switzerland",
            "Faculty of Science, University of Basel, Basel, Switzerland"
        ],
        "Penelope Vounatsou": [
            "Swiss Tropical and Public Health Institute, Basel, Switzerland",
            "Faculty of Science, University of Basel, Basel, Switzerland"
        ]
    }
}