{
    "URL": "https://doi.org/10.1371/journal.pntd.0000855",
    "Published": "October 26, 2010",
    "Subject_Areas": [
        "Leishmaniasis",
        "Audiology",
        "Drug therapy",
        "Phase III clinical investigation",
        "Sudan",
        "Adverse events",
        "India",
        "Pharmacokinetics"
    ],
    "Authors": {
        "Ahmed M. Musa": [
            "Institute of Endemic Diseases, University of Khartoum, Khartoum, Sudan"
        ],
        "Brima Younis": [
            "Institute of Endemic Diseases, University of Khartoum, Khartoum, Sudan"
        ],
        "Ahmed Fadlalla": [
            "Faculty of Medicine, Gedaref University, Gedaref, Sudan"
        ],
        "Catherine Royce": [
            "Drugs for Neglected Diseases initiative (DNDi), Geneva, Switzerland"
        ],
        "Manica Balasegaram": [
            "Drugs for Neglected Diseases initiative (DNDi), Geneva, Switzerland"
        ],
        "Monique Wasunna": [
            "Centre for Clinical Research, Kenya Medical Research Institute (KEMRI), Nairobi, Kenya"
        ],
        "Asrat Hailu": [
            "Addis Ababa University, Addis Ababa, Ethiopia"
        ],
        "Tansy Edwards": [
            "London School of Hygiene and Tropical Medicine, London, United Kingdom"
        ],
        "Raymond Omollo": [
            "Centre for Clinical Research, Kenya Medical Research Institute (KEMRI), Nairobi, Kenya"
        ],
        "Mahmoud Mudawi": [
            "Institute of Endemic Diseases, University of Khartoum, Khartoum, Sudan"
        ],
        "Gilbert Kokwaro": [
            "Faculty of Pharmacy, University of Nairobi, Nairobi, Kenya",
            "Consortium for National Health Research (CNHR), Nairobi, Kenya"
        ],
        "Ahmed El-Hassan": [
            "Institute of Endemic Diseases, University of Khartoum, Khartoum, Sudan"
        ],
        "Eltahir Khalil": [
            "Institute of Endemic Diseases, University of Khartoum, Khartoum, Sudan"
        ]
    }
}