{
    "Title": "Cystic Echinococcosis Epidemiology in Spain Based on Hospitalization Records, 1997-2012",
    "URL": "https://doi.org/10.1371/journal.pntd.0004942",
    "Published": "August 22, 2016",
    "Subject_Areas": [
        "Echinococcosis",
        "Spain",
        "Epidemiology",
        "Cystic echinococcosis",
        "Hospitalizations",
        "Surgical and invasive medical procedures",
        "Cestodes",
        "Europe"
    ],
    "Authors": {
        "Zaida Herrador": [
            "National Centre for Tropical Medicine, Health Institute Carlos III (ISCIII in Spanish), Madrid, Spain",
            "Network Biomedical Research on Tropical Diseases (RICET in Spanish), Madrid, Spain"
        ],
        "Mar Siles-Lucas": [
            "Laboratory of Parasitology, Instituto de Recursos Naturales y Agrobiología de Salamanca (IRNASA), Consejo Superior de Investigaciones Científicas (CSIC), Salamanca, Spain"
        ],
        "Pilar Aparicio": [
            "National Centre for Tropical Medicine, Health Institute Carlos III (ISCIII in Spanish), Madrid, Spain",
            "Network Biomedical Research on Tropical Diseases (RICET in Spanish), Madrid, Spain"
        ],
        "Rogelio Lopez-Velez": [
            "Network Biomedical Research on Tropical Diseases (RICET in Spanish), Madrid, Spain",
            "National Referral Centre for Tropical Diseases, Infectious Diseases Department, Ramón y Cajal Hospital, Instituto Ramón y Cajal de Investigación Sanitaria, Madrid, Spain"
        ],
        "Alin Gherasim": [
            "National Centre of Epidemiology, Health Institute Carlos III (ISCIII), Madrid, Spain"
        ],
        "Teresa Garate": [
            "Network Biomedical Research on Tropical Diseases (RICET in Spanish), Madrid, Spain",
            "National Centre of Microbiology, Health Institute Carlos III (ISCIII), Madrid, Spain"
        ],
        "Agustín Benito": [
            "National Centre for Tropical Medicine, Health Institute Carlos III (ISCIII in Spanish), Madrid, Spain",
            "Network Biomedical Research on Tropical Diseases (RICET in Spanish), Madrid, Spain"
        ]
    }
}