{
    "Title": "The Short Non-Coding Transcriptome of the Protozoan Parasite Trypanosoma cruzi",
    "URL": "https://doi.org/10.1371/journal.pntd.0001283",
    "Published": "August 30, 2011",
    "Subject_Areas": [
        "Small nucleolar RNA",
        "RNA sequencing",
        "Transfer RNA",
        "Small interfering RNA",
        "Trypanosoma cruzi",
        "Sequence alignment",
        "Genomics",
        "Ribosomal RNA"
    ],
    "Authors": {
        "Oscar Franzén": [
            "Science for Life Laboratory, Department of Cell and Molecular Biology, Karolinska Institutet, Stockholm, Sweden"
        ],
        "Erik Arner": [
            "RIKEN Omics Sciences Center, RIKEN Yokohama Institute, Yokohama, Kanagawa, Japan"
        ],
        "Marcela Ferella": [
            "Rudbeck Laboratory, Department of Immunology, Genetics and Pathology, Uppsala University, Uppsala, Sweden"
        ],
        "Daniel Nilsson": [
            "Institute of Cell Biology, University of Bern, Bern, Switzerland"
        ],
        "Patricia Respuela": [
            "Rudbeck Laboratory, Department of Immunology, Genetics and Pathology, Uppsala University, Uppsala, Sweden"
        ],
        "Piero Carninci": [
            "RIKEN Omics Sciences Center, RIKEN Yokohama Institute, Yokohama, Kanagawa, Japan"
        ],
        "Yoshihide Hayashizaki": [
            "RIKEN Omics Sciences Center, RIKEN Yokohama Institute, Yokohama, Kanagawa, Japan"
        ],
        "Lena Åslund": [
            "Rudbeck Laboratory, Department of Immunology, Genetics and Pathology, Uppsala University, Uppsala, Sweden"
        ],
        "Björn Andersson": [
            "Science for Life Laboratory, Department of Cell and Molecular Biology, Karolinska Institutet, Stockholm, Sweden"
        ],
        "Carsten O. Daub": [
            "RIKEN Omics Sciences Center, RIKEN Yokohama Institute, Yokohama, Kanagawa, Japan"
        ]
    }
}