{
    "URL": "https://doi.org/10.1371/journal.pntd.0010501",
    "Published": "June 6, 2022",
    "Subject_Areas": [
        "Insecticides",
        "Aedes aegypti",
        "Indonesia",
        "Mosquitoes",
        "Dengue fever",
        "Cities",
        "Organophosphates",
        "Java"
    ],
    "Authors": {
        "Christina Natalina Silalahi": [
            "Department of Entomology, National Chung Hsing University, Taichung, Taiwan"
        ],
        "Wu-Chun Tu": [
            "Department of Entomology, National Chung Hsing University, Taichung, Taiwan"
        ],
        "Niann-Tai Chang": [
            "Department of Plant Medicine, National Pingtung University of Science and Technology, Pingtung, Taiwan"
        ],
        "G. Veera Singham": [
            "Centre for Chemical Biology, Universiti Sains Malaysia, Bayan Lepas, Penang, Malaysia"
        ],
        "Intan Ahmad": [
            "School of Life Sciences and Technology, Institut Teknologi Bandung, Bandung, West Java, Indonesia"
        ],
        "Kok-Boon Neoh": [
            "Department of Entomology, National Chung Hsing University, Taichung, Taiwan"
        ]
    }
}