{
    "URL": "https://doi.org/10.1371/journal.pntd.0008534",
    "Published": "July 31, 2020",
    "Subject_Areas": [
        "Mast cells",
        "Nematode infections",
        "Mouse models",
        "Mites",
        "Helminth infections",
        "Vascular permeability",
        "Parasitic diseases",
        "Blood"
    ],
    "Authors": {
        "Lara Christine Linnemann": [
            "Bernhard Nocht Institute for Tropical Medicine, Hamburg, Germany"
        ],
        "Martina Reitz": [
            "Bernhard Nocht Institute for Tropical Medicine, Hamburg, Germany"
        ],
        "Thorsten B. Feyerabend": [
            "Division for Cellular Immunology, German Cancer Research Center, Heidelberg, Germany"
        ],
        "Minka Breloer": [
            "Bernhard Nocht Institute for Tropical Medicine, Hamburg, Germany",
            "Department of Biology, University of Hamburg, Hamburg, Germany"
        ],
        "Wiebke Hartmann": [
            "Bernhard Nocht Institute for Tropical Medicine, Hamburg, Germany"
        ]
    }
}