{
    "Title": "A novel cell-free method to culture Schistosoma mansoni from cercariae to juvenile worm stages for in vitro drug testing",
    "URL": "https://doi.org/10.1371/journal.pntd.0006590",
    "Published": "January 28, 2019",
    "Subject_Areas": [
        "Schistosoma mansoni",
        "Larvae",
        "Drug screening",
        "Parasitic diseases",
        "Penicillin",
        "Streptomycin",
        "Schistosomiasis",
        "Artemether"
    ],
    "Authors": {
        "Sören Frahm": [
            "Institute for Medical Microbiology, Immunology and Hygiene, Technische Universität München, Munich, Germany"
        ],
        "Anisuzzaman Anisuzzaman": [
            "Institute for Medical Microbiology, Immunology and Hygiene, Technische Universität München, Munich, Germany",
            "Department of Parasitology, Bangladesh Agricultural University, Mymensingh, Bangladesh"
        ],
        "Ulrich Fabien Prodjinotho": [
            "Institute for Medical Microbiology, Immunology and Hygiene, Technische Universität München, Munich, Germany"
        ],
        "Nermina Vejzagić": [
            "Institute for Medical Microbiology, Immunology and Hygiene, Technische Universität München, Munich, Germany"
        ],
        "Admar Verschoor": [
            "Institute for Systemic Inflammation Research, Universität zu Lübeck, Lübeck, Germany"
        ],
        "Clarissa Prazeres da Costa": [
            "Institute for Medical Microbiology, Immunology and Hygiene, Technische Universität München, Munich, Germany"
        ]
    }
}