{
    "URL": "https://doi.org/10.1371/journal.pntd.0000584",
    "Published": "January 19, 2010",
    "Subject_Areas": [
        "Leishmaniasis",
        "Dogs",
        "Brazil",
        "Pets and companion animals",
        "Parasitology",
        "Parasitic diseases",
        "Sand flies",
        "Insecticides"
    ],
    "Authors": {
        "Gustavo A. S. Romero": [
            "N\u00facleo de Medicina Tropical, Faculdade de Medicina, Universidade de Bras\u00edlia, Bras\u00edlia, Distrito Federal, Brazil"
        ],
        "Marleen Boelaert": [
            "Epidemiology and Disease Control Unit, Institute of Tropical Medicine, Antwerp, Belgium"
        ]
    }
}