{
    "Title": "DNA vaccination induced protective immunity against SARS CoV-2 infection in hamsterss",
    "URL": "https://doi.org/10.1371/journal.pntd.0009374",
    "Published": "May 27, 2021",
    "Subject_Areas": [
        "SARS CoV 2",
        "Antibodies",
        "Enzyme-linked immunoassays",
        "DNA vaccination",
        "Hamsters",
        "COVID 19",
        "Immune response",
        "Viral vaccines"
    ],
    "Authors": {
        "Kit Man Chai": [
            "National Institute of Infectious Diseases and Vaccinology, National Health Research Institutes, Miaoli, Taiwan"
        ],
        "Tsai-Teng Tzeng": [
            "National Institute of Infectious Diseases and Vaccinology, National Health Research Institutes, Miaoli, Taiwan"
        ],
        "Kuan-Yin Shen": [
            "National Institute of Infectious Diseases and Vaccinology, National Health Research Institutes, Miaoli, Taiwan"
        ],
        "Hung-Chun Liao": [
            "National Institute of Infectious Diseases and Vaccinology, National Health Research Institutes, Miaoli, Taiwan",
            "Department of Life Sciences, National Tsing Hua University, Hsinchu, Taiwan"
        ],
        "Jhe-Jhih Lin": [
            "National Institute of Infectious Diseases and Vaccinology, National Health Research Institutes, Miaoli, Taiwan"
        ],
        "Mei-Yu Chen": [
            "National Institute of Infectious Diseases and Vaccinology, National Health Research Institutes, Miaoli, Taiwan"
        ],
        "Guann-Yi Yu": [
            "National Institute of Infectious Diseases and Vaccinology, National Health Research Institutes, Miaoli, Taiwan"
        ],
        "Horng-Yunn Dou": [
            "National Institute of Infectious Diseases and Vaccinology, National Health Research Institutes, Miaoli, Taiwan"
        ],
        "Ching-Len Liao": [
            "National Institute of Infectious Diseases and Vaccinology, National Health Research Institutes, Miaoli, Taiwan"
        ],
        "Hsin-Wei Chen": [
            "National Institute of Infectious Diseases and Vaccinology, National Health Research Institutes, Miaoli, Taiwan",
            "Graduate Institute of Biomedical Sciences, China Medical University, Taichung, Taiwan",
            "Graduate Institute of Medicine, College of Medicine, Kaohsiung Medical University, Kaohsiung, Taiwan"
        ],
        "Shih-Jen Liu": [
            "National Institute of Infectious Diseases and Vaccinology, National Health Research Institutes, Miaoli, Taiwan",
            "Graduate Institute of Biomedical Sciences, China Medical University, Taichung, Taiwan",
            "Graduate Institute of Medicine, College of Medicine, Kaohsiung Medical University, Kaohsiung, Taiwan"
        ]
    }
}