{
    "Title": "Profile of Trypanosoma cruzi Infection in a Tropical Medicine Reference Center, Northern Italy",
    "URL": "https://doi.org/10.1371/journal.pntd.0003361",
    "Published": "December 11, 2014",
    "Subject_Areas": [
        "Chagas disease",
        "Italy",
        "Electrocardiography",
        "Echocardiography",
        "Colon",
        "Blood counts",
        "Barium",
        "Esophagus"
    ],
    "Authors": {
        "Federico Gobbi": [
            "Centre for Tropical Diseases (CTD), Sacro Cuore Hospital, Negrar, Verona, Italy"
        ],
        "Andrea Angheben": [
            "Centre for Tropical Diseases (CTD), Sacro Cuore Hospital, Negrar, Verona, Italy"
        ],
        "Mariella Anselmi": [
            "Centre for Tropical Diseases (CTD), Sacro Cuore Hospital, Negrar, Verona, Italy",
            "Centre for Community Epidemiology and Tropical Medicine (CECOMET), Esmeraldas, Ecuador"
        ],
        "Chiara Postiglione": [
            "Prevention Department, ULSS 20, Verona, Italy"
        ],
        "Ernestina Repetto": [
            "Operational Center Bruxelles, Médecins Sans Frontières, Bruxelles, Belgium"
        ],
        "Dora Buonfrate": [
            "Centre for Tropical Diseases (CTD), Sacro Cuore Hospital, Negrar, Verona, Italy"
        ],
        "Stefania Marocco": [
            "Centre for Tropical Diseases (CTD), Sacro Cuore Hospital, Negrar, Verona, Italy"
        ],
        "Stefano Tais": [
            "Centre for Tropical Diseases (CTD), Sacro Cuore Hospital, Negrar, Verona, Italy"
        ],
        "Andrea Chiampan": [
            "Cardiology Unit, Sacro Cuore Hospital, Negrar, Verona, Italy"
        ],
        "Paride Mainardi": [
            "Radiology Unit, Sacro Cuore Hospital, Negrar, Verona, Italy"
        ],
        "Zeno Bisoffi": [
            "Centre for Tropical Diseases (CTD), Sacro Cuore Hospital, Negrar, Verona, Italy"
        ]
    }
}