{
    "URL": "https://doi.org/10.1371/journal.pntd.0011441",
    "Published": "July 7, 2023",
    "Subject_Areas": [
        "Enzyme-linked immunoassays",
        "Trachoma",
        "Antibodies",
        "Serology",
        "Islands",
        "Kiribati",
        "Enzyme assays",
        "Public and occupational health"
    ],
    "Authors": {
        "E. Brook Goodhew": [
            "VAAS Contractors, Atlanta Georgia"
        ],
        "Raebwebwe Taoaba": [
            "Ministry of Health and Medical Services, South Tarawa, Kiribati"
        ],
        "Emma M. Harding-Esch": [
            "Clinical Research Department, London School of Hygiene & Tropical Medicine, London, United Kingdom"
        ],
        "Sarah E. Gwyn": [
            "Centers for Disease Control and Prevention, Atlanta Georgia"
        ],
        "Ana Bakhtiari": [
            "International Trachoma Initiative, Task Force for Global Health, Atlanta, Georgia"
        ],
        "Robert Butcher": [
            "Clinical Research Department, London School of Hygiene & Tropical Medicine, London, United Kingdom"
        ],
        "Anasaini Cama": [
            "The Fred Hollows Foundation, Melbourne, Australia"
        ],
        "Sarah Anne J. Guagliardo": [
            "Centers for Disease Control and Prevention, Atlanta Georgia"
        ],
        "Cristina Jimenez": [
            "Sightsavers International, London United Kingdom"
        ],
        "Caleb D. Mpyet": [
            "Department of Ophthalmology, College of Health Sciences, University of Jos; Jos, Nigeria, and Sightsavers, Nigeria Country Office, Kaduna, Nigeria"
        ],
        "Kab Tun": [
            "Ministry of Health and Medical Services, South Tarawa, Kiribati"
        ],
        "Karana Wickens": [
            "Oak Ridge Institute for Science and Education, Oak Ridge, Tennessee"
        ],
        "Anthony W. Solomon": [
            "Department of Control of Neglected Tropical Diseases, World Health Organization, Geneva, Switzerland"
        ],
        "Diana L. Martin": [
            "Centers for Disease Control and Prevention, Atlanta Georgia"
        ],
        "Rabebe Tekeraoi": [
            "Ministry of Health and Medical Services, South Tarawa, Kiribati"
        ]
    }
}