{
    "URL": "https://doi.org/10.1371/journal.pntd.0008747",
    "Published": "November 12, 2020",
    "Subject_Areas": [
        "Scrub typhus",
        "Enzyme-linked immunoassays",
        "Polymerase chain reaction",
        "Diagnostic medicine",
        "Dengue fever",
        "Eschar",
        "Serology",
        "Serodiagnosis"
    ],
    "Authors": {
        "Kavitha Kannan": [
            "Department of Infectious Diseases, Christian Medical College, Vellore, Tamil Nadu, India"
        ],
        "Rebecca John": [
            "Department of Infectious Diseases, Christian Medical College, Vellore, Tamil Nadu, India"
        ],
        "Debasree Kundu": [
            "Department of Infectious Diseases, Christian Medical College, Vellore, Tamil Nadu, India"
        ],
        "Divya Dayanand": [
            "Department of Infectious Diseases, Christian Medical College, Vellore, Tamil Nadu, India"
        ],
        "Kundavaram P. P. Abhilash": [
            "Department of Emergency Medicine, Christian Medical College, Vellore, Tamil Nadu, India"
        ],
        "Alice Joan Mathuram": [
            "Department of Medicine, Christian Medical College, Vellore, Tamil Nadu, India"
        ],
        "Anand Zachariah": [
            "Department of Medicine, Christian Medical College, Vellore, Tamil Nadu, India"
        ],
        "Sowmya Sathyendra": [
            "Department of Medicine, Christian Medical College, Vellore, Tamil Nadu, India"
        ],
        "Samuel G. Hansdak": [
            "Department of Medicine, Christian Medical College, Vellore, Tamil Nadu, India"
        ],
        "O. C. Abraham": [
            "Department of Medicine, Christian Medical College, Vellore, Tamil Nadu, India"
        ],
        "Karthik Gunasekaran": [
            "Department of Medicine, Christian Medical College, Vellore, Tamil Nadu, India"
        ],
        "Ramya Iyadurai": [
            "Department of Medicine, Christian Medical College, Vellore, Tamil Nadu, India"
        ],
        "Asha M. Abraham": [
            "Department of Clinical Virology, Christian Medical College, Vellore, Tamil Nadu, India"
        ],
        "John Antony Jude Prakash": [
            "Department of Microbiology, Christian Medical College, Vellore, Tamil Nadu, India"
        ],
        "Binesh Lal Yesudhason": [
            "Department of Microbiology, Christian Medical College, Vellore, Tamil Nadu, India"
        ],
        "Balaji Veeraraghavan": [
            "Department of Microbiology, Christian Medical College, Vellore, Tamil Nadu, India"
        ],
        "M. L. Kavitha": [
            "Department of Haematology, Christian Medical College, Vellore, Tamil Nadu, India"
        ],
        "Linda R. Jose": [
            "JSS Medical College, Mysuru, Karnataka India"
        ],
        "M. N. Sumana": [
            "JSS Medical College, Mysuru, Karnataka India"
        ],
        "Kavitha Saravu": [
            "Department of Infectious Diseases, Kasturba Medical College, Manipal, Manipal Academy of Higher Education, Karnataka, India"
        ],
        "George M. Varghese": [
            "Department of Infectious Diseases, Christian Medical College, Vellore, Tamil Nadu, India"
        ]
    }
}