{
    "Title": "Is Dengue Vector Control Deficient in Effectiveness or Evidence?: Systematic Review and Meta-analysis",
    "URL": "https://doi.org/10.1371/journal.pntd.0004551",
    "Published": "March 17, 2016",
    "Subject_Areas": [
        "Dengue fever",
        "Randomized controlled trials",
        "Insecticides",
        "Infectious disease control",
        "Aedes aegypti",
        "Metaanalysis",
        "Mosquitoes",
        "Environmental management"
    ],
    "Authors": {
        "Leigh R. Bowman": [
            "Department of Vector Biology, Liverpool School of Tropical Medicine, Liverpool, United Kingdom"
        ],
        "Sarah Donegan": [
            "Department of Biostatistics, University of Liverpool, Liverpool, United Kingdom"
        ],
        "Philip J. McCall": [
            "Department of Vector Biology, Liverpool School of Tropical Medicine, Liverpool, United Kingdom"
        ]
    }
}