{
    "URL": "https://doi.org/10.1371/journal.pntd.0012288",
    "Published": "June 24, 2024",
    "Subject_Areas": [
        "Parasitic diseases",
        "Myoblasts",
        "Trypanosoma cruzi",
        "Cell differentiation",
        "Parasite replication",
        "Trypomastigotes",
        "Host cells",
        "Cell motility"
    ],
    "Authors": {
        "Jos\u00e9 Mar\u00eda Eloy Contreras-Ortiz": [
            "Centro de Investigaci\u00f3n y de Estudios Avanzados del IPN, Unidad Monterrey, Apodaca, Nuevo Leon, M\u00e9xico",
            "Departamento de Biomedicina Molecular, Centro de Investigaci\u00f3n y de Estudios Avanzados del IPN, CDMX, Ciudad de M\u00e9xico, M\u00e9xico",
            "Centro de Investigaci\u00f3n en Ciencias Biol\u00f3gicas Aplicadas, Universidad Aut\u00f3noma del Estado de M\u00e9xico, Toluca, M\u00e9xico"
        ],
        "Daniel Hern\u00e1ndez-Mendoza": [
            "Centro de Investigaci\u00f3n y de Estudios Avanzados del IPN, Unidad Monterrey, Apodaca, Nuevo Leon, M\u00e9xico",
            "Departamento de Biomedicina Molecular, Centro de Investigaci\u00f3n y de Estudios Avanzados del IPN, CDMX, Ciudad de M\u00e9xico, M\u00e9xico"
        ],
        "Claudia M\u00e1rquez-Due\u00f1as": [
            "Centro de Investigaci\u00f3n y de Estudios Avanzados del IPN, Unidad Monterrey, Apodaca, Nuevo Leon, M\u00e9xico"
        ],
        "Rebeca Manning-Cela": [
            "Departamento de Biomedicina Molecular, Centro de Investigaci\u00f3n y de Estudios Avanzados del IPN, CDMX, Ciudad de M\u00e9xico, M\u00e9xico"
        ],
        "Mois\u00e9s Santill\u00e1n": [
            "Centro de Investigaci\u00f3n y de Estudios Avanzados del IPN, Unidad Monterrey, Apodaca, Nuevo Leon, M\u00e9xico"
        ]
    }
}