{
    "Title": "Molecular Characterization of Cryptosporidium spp. among Children in Rural Ghana",
    "URL": "https://doi.org/10.1371/journal.pntd.0003551",
    "Published": "March 6, 2015",
    "Subject_Areas": [
        "Cryptosporidium parvum",
        "Cryptosporidium",
        "Diarrhea",
        "Cardiobacterium hominis",
        "Children",
        "Ghana",
        "Vomiting",
        "Pediatric infections"
    ],
    "Authors": {
        "Daniel Eibach": [
            "Bernhard Nocht Institute for Tropical Medicine (BNITM), Hamburg, Germany",
            "German Center for Infection Research (DZIF), partner site Hamburg-Borstel-Lübeck, Germany"
        ],
        "Ralf Krumkamp": [
            "Bernhard Nocht Institute for Tropical Medicine (BNITM), Hamburg, Germany",
            "German Center for Infection Research (DZIF), partner site Hamburg-Borstel-Lübeck, Germany"
        ],
        "Hassan M. Al-Emran": [
            "Bernhard Nocht Institute for Tropical Medicine (BNITM), Hamburg, Germany"
        ],
        "Nimako Sarpong": [
            "Kumasi Centre for Collaborative Research in Tropical Medicine (KCCR), Kumasi, Ghana"
        ],
        "Ralf Matthias Hagen": [
            "Department of Tropical Medicine at the BNITM, German Armed Forces Hospital of Hamburg, Hamburg, Germany"
        ],
        "Yaw Adu-Sarkodie": [
            "Kwame Nkrumah University of Science and Technology (KNUST), Kumasi, Ghana"
        ],
        "Egbert Tannich": [
            "Bernhard Nocht Institute for Tropical Medicine (BNITM), Hamburg, Germany",
            "German Center for Infection Research (DZIF), partner site Hamburg-Borstel-Lübeck, Germany"
        ],
        "Jürgen May": [
            "Bernhard Nocht Institute for Tropical Medicine (BNITM), Hamburg, Germany",
            "German Center for Infection Research (DZIF), partner site Hamburg-Borstel-Lübeck, Germany"
        ]
    }
}