{
    "URL": "https://doi.org/10.1371/journal.pntd.0002235",
    "Published": "May 23, 2013",
    "Subject_Areas": [
        "Parasitic diseases",
        "Echinococcosis",
        "Enzyme-linked immunoassays",
        "Animal models of infection",
        "Drug therapy",
        "Cancer treatment",
        "Vesicles",
        "Antibodies"
    ],
    "Authors": {
        "Tatiana K\u00fcster": [
            "Institute of Parasitology, Vetsuisse Faculty, University of Berne, Berne, Switzerland"
        ],
        "Corina Hermann": [
            "Institute of Parasitology, Vetsuisse Faculty, University of Berne, Berne, Switzerland"
        ],
        "Andrew Hemphill": [
            "Institute of Parasitology, Vetsuisse Faculty, University of Berne, Berne, Switzerland"
        ],
        "Bruno Gottstein": [
            "Institute of Parasitology, Vetsuisse Faculty, University of Berne, Berne, Switzerland"
        ],
        "Markus Spiliotis": [
            "Institute of Parasitology, Vetsuisse Faculty, University of Berne, Berne, Switzerland"
        ]
    }
}