{
    "Title": "Pediatric Cutaneous Leishmaniasis in an Endemic Region in Turkey: A Retrospective Analysis of 8786 Cases during 1998-2014",
    "URL": "https://doi.org/10.1371/journal.pntd.0004835",
    "Published": "July 14, 2016",
    "Subject_Areas": [
        "Lesions",
        "Pediatrics",
        "Leishmaniasis",
        "Age groups",
        "Turkey (country)",
        "Pediatric infections",
        "Epidemiology",
        "Ulcers"
    ],
    "Authors": {
        "Mustafa Aksoy": [
            "Department of Dermatology, Harran University School of Medicine, Sanliurfa, Turkey"
        ],
        "Nebiye Doni": [
            "Department of Microbiology, Harran University School of Medicine, Sanliurfa, Turkey"
        ],
        "Hatice Uce Ozkul": [
            "Department of Dermatology, Yuzuncu Y\u0131l University School of Medicine, Van, Turkey"
        ],
        "Yavuz Yesilova": [
            "Ministry of Health, Health Sciences University, Van Training and Research Hospital, Dermatology Clinic, Van, Turkey"
        ],
        "Nurittin Ardic": [
            "Department of Microbiology, Gulhane Military Medical Academy, Ankara, Turkey"
        ],
        "Abdullah Yesilova": [
            "Department of Biostatistics, Yuzuncu Y\u0131l University School of Medicine, Van, Turkey"
        ],
        "Jennifer Ahn-Jarvis": [
            "Biosciences, College of Dentistry, Ohio State University, Columbus, Ohio, United States of America"
        ],
        "Steve Oghumu": [
            "Environmental Health Sciences, College of Public Health, Ohio State University, Columbus, Ohio, United States of America"
        ],
        "Cesar Terrazas": [
            "Department of Pathology, Ohio State University Medical Center, Columbus, Ohio, United States of America"
        ],
        "Abhay R. Satoskar": [
            "Department of Pathology, Ohio State University Medical Center, Columbus, Ohio, United States of America"
        ]
    }
}