{
    "URL": "https://doi.org/10.1371/journal.pntd.0001255",
    "Published": "August 2, 2011",
    "Subject_Areas": [
        "Snakebite",
        "Depression",
        "Post-traumatic stress disorder",
        "Clinical psychology",
        "Morbidity",
        "Snakes",
        "Employment",
        "Anxiety disorders"
    ],
    "Authors": {
        "Shehan S. Williams": [
            "Department of Psychiatry, Faculty of Medicine, University of Kelaniya, Ragama, Sri Lanka"
        ],
        "Chamara A. Wijesinghe": [
            "Department of Psychiatry, Faculty of Medicine, University of Kelaniya, Ragama, Sri Lanka"
        ],
        "Shaluka F. Jayamanne": [
            "Department of Medicine, Faculty of Medicine, University of Kelaniya, Ragama, Sri Lanka"
        ],
        "Nicholas A. Buckley": [
            "South Asian Clinical Toxicology Research Collaboration, University of Peradeniya, Peradeniya, Sri Lanka",
            "Prince of Wales Clinical School, University of New South Wales, Sydney, Australia"
        ],
        "Andrew H. Dawson": [
            "South Asian Clinical Toxicology Research Collaboration, University of Peradeniya, Peradeniya, Sri Lanka",
            "Prince of Wales Clinical School, University of New South Wales, Sydney, Australia"
        ],
        "David G. Lalloo": [
            "Liverpool School of Tropical Medicine, Liverpool, United Kingdom"
        ],
        "H. Janaka de Silva": [
            "Department of Medicine, Faculty of Medicine, University of Kelaniya, Ragama, Sri Lanka"
        ]
    }
}