{
    "Title": "A pilot study of dimeticone oils versus sodium carbonate treatment for tungiasis: A randomized cohort trial in Homa Bay County, Kenya",
    "URL": "https://doi.org/10.1371/journal.pntd.0012341",
    "Published": "July 23, 2024",
    "Subject_Areas": [
        "Fleas",
        "Sodium carbonates",
        "Pain",
        "Inflammation",
        "Pruritus",
        "Kenya",
        "Petroleum",
        "Schools"
    ],
    "Authors": {
        "Kana Suzuki": [
            "School ofTropical Medicine and Global Health, Nagasaki University, Nagasaki, Japan"
        ],
        "Yasuhiko Kamiya": [
            "School ofTropical Medicine and Global Health, Nagasaki University, Nagasaki, Japan"
        ],
        "Chris Smith": [
            "School ofTropical Medicine and Global Health, Nagasaki University, Nagasaki, Japan",
            "Department of Clinical Research, Faculty of Infectious and Tropical Diseases, London School of Hygiene and Tropical Medicine, London, United Kingdom"
        ],
        "Satoshi Kaneko": [
            "School ofTropical Medicine and Global Health, Nagasaki University, Nagasaki, Japan",
            "Department of Ecoepidemiology, Institute of Tropical Medicine, Nagasaki University, Nagasaki, Japan"
        ],
        "Gordon Okomo": [
            "Ministry of Health Homa Bay County, Homa Bay, Kenya"
        ],
        "Asiko Ongaya": [
            "Kenya Medical Research Institute, Nairobi, Kenya"
        ],
        "Evans Amukoye": [
            "Kenya Medical Research Institute, Nairobi, Kenya"
        ]
    }
}