{
    "URL": "https://doi.org/10.1371/journal.pntd.0008535",
    "Published": "August 19, 2020",
    "Subject_Areas": [
        "Dengue fever",
        "Epidemiology",
        "Infectious disease surveillance",
        "Dengue virus",
        "Guatemala",
        "Age groups",
        "Enzyme-linked immunoassays",
        "Public and occupational health"
    ],
    "Authors": {
        "Leticia del Carmen Castillo Signor": [
            "Ministerio de Salud Publica y Asistencia Social de Guatemala, Guatemala City, Guatemala"
        ],
        "Thomas Edwards": [
            "Centre for Drugs and Diagnostics Research, Liverpool School of Tropical Medicine, Liverpool, United Kingdom"
        ],
        "Luis E. Escobar": [
            "Department of Fish and Wildlife Conservation, Virginia Tech, Blacksburg, VA, United States of America"
        ],
        "Yolanda Mencos": [
            "Ministerio de Salud Publica y Asistencia Social de Guatemala, Guatemala City, Guatemala"
        ],
        "Agnes Matope": [
            "Tropical Clinical Trials Unit. Liverpool School of Tropical Medicine, Liverpool, United Kingdom"
        ],
        "Mariana Castaneda-Guzman": [
            "Department of Fish and Wildlife Conservation, Virginia Tech, Blacksburg, VA, United States of America"
        ],
        "Emily R. Adams": [
            "Centre for Drugs and Diagnostics Research, Liverpool School of Tropical Medicine, Liverpool, United Kingdom"
        ],
        "Luis E. Cuevas": [
            "Centre for Drugs and Diagnostics Research, Liverpool School of Tropical Medicine, Liverpool, United Kingdom",
            "Tropical Clinical Trials Unit. Liverpool School of Tropical Medicine, Liverpool, United Kingdom"
        ]
    }
}